evil_pkg1/__init__.py
evil_pkg1-0.2.dist-info/METADATA
evil_pkg1-0.2.dist-info/WHEEL
evil_pkg1-0.2.dist-info/top_level.txt
evil_pkg1-0.2.dist-info/RECORD
