Metadata-Version: 2.2
Name: evil-pkg1
Version: 0.2
Summary: Just a harmless package :)
Dynamic: summary
